Metadata-Version: 1.1
Name: sara
Version: 1.0
Summary: Virtual Assistant
Home-page: https://github.com/SubrataSarkar32/sara
Author: Subrata Sarkar
Author-email: subrotosarkar32@gmail.com
License: GNU GPL v2 or later
Platform: UNKNOWN
Classifier: Development Status :: 3 - Alpha
Classifier: Intended Audience :: Developers
Classifier: License :: OSI Approved :: GNU General Public License v2 or later (GPLv2+)
Classifier: Operating System :: OS Independent
Classifier: Programming Language :: Python
Classifier: Programming Language :: Python :: 2.7
